rnabert/__init__.py
rnabert/_version.py
rnabert/config.json
rnabert/configuration_rnabert.py
rnabert/modeling_rnabert.py
rnabert/special_tokens_map.json
rnabert/tokenization_rnabert.py
rnabert/tokenizer_config.json
rnabert/vocab.txt
rnabert-0.0.1.dist-info/METADATA
rnabert-0.0.1.dist-info/WHEEL
rnabert-0.0.1.dist-info/top_level.txt
rnabert-0.0.1.dist-info/RECORD
